Workbook

Sheet Summary
A1: Bookings Platform (GetYourGuide-style) - API Design
A2: All endpoints are prefixed with /api/v1. Track your progress with the Status column on the 'API Endpoints' sheet.
A4: Module | B4: Total endpoints | C4: Not started | D4: In progress | E4: Done | F4: % Done
A5: Customer | B5: =COUNTIF('API Endpoints'!$B:$B,A5) -> 63 | C5: =COUNTIFS('API Endpoints'!$B:$B,$A5,'API Endpoints'!$G:$G,"Not started") -> 63 | D5: =COUNTIFS('API Endpoints'!$B:$B,$A5,'API Endpoints'!$G:$G,"In progress") -> 0 | E5: =COUNTIFS('API Endpoints'!$B:$B,$A5,'API Endpoints'!$G:$G,"Done") -> 0 | F5: =IF(B5=0,0,E5/B5) -> 0
A6: Supplier | B6: =COUNTIF('API Endpoints'!$B:$B,A6) -> 26 | C6: =COUNTIFS('API Endpoints'!$B:$B,$A6,'API Endpoints'!$G:$G,"Not started") -> 26 | D6: =COUNTIFS('API Endpoints'!$B:$B,$A6,'API Endpoints'!$G:$G,"In progress") -> 0 | E6: =COUNTIFS('API Endpoints'!$B:$B,$A6,'API Endpoints'!$G:$G,"Done") -> 0 | F6: =IF(B6=0,0,E6/B6) -> 0
A7: Admin | B7: =COUNTIF('API Endpoints'!$B:$B,A7) -> 40 | C7: =COUNTIFS('API Endpoints'!$B:$B,$A7,'API Endpoints'!$G:$G,"Not started") -> 35 | D7: =COUNTIFS('API Endpoints'!$B:$B,$A7,'API Endpoints'!$G:$G,"In progress") -> 0 | E7: =COUNTIFS('API Endpoints'!$B:$B,$A7,'API Endpoints'!$G:$G,"Done") -> 5 | F7: =IF(B7=0,0,E7/B7) -> 0.125
A8: Total | B8: =SUM(B5:B7) -> 129 | C8: =SUM(C5:C7) -> 124 | D8: =SUM(D5:D7) -> 0 | E8: =SUM(E5:E7) -> 5 | F8: =IF(B8=0,0,E8/B8) -> 0.03875969
A10: Design stats
A11: Entities / tables | B11: =COUNTA('Domain Entities'!$A:$A)-1 -> 33
A12: Fields (columns) | B12: =COUNTA('Entity Fields'!$A:$A)-1 -> 335
A13: Enums | B13: =SUMPRODUCT((Enums!$A$2:$A$500<>"")/COUNTIF(Enums!$A$2:$A$500,Enums!$A$2:$A$500&"")) -> 19
A14: DTO classes (catalog) | B14: =COUNTA('DTO Catalog'!$A:$A)-1 -> 43
A16: Sheets in this workbook
A17: API Endpoints - every endpoint with module, group, method, path, purpose, status
A18: Domain Entities - entities and their tables, with field counts
A19: Entity Fields - every column: Java/PostgreSQL types, keys, defaults, validation, DTO flags
A20: Relationships - cardinality, FK columns and JPA notes
A21: Enums - all enum values and where they are used
A22: Constraints & Indexes - unique, check and index definitions per table
A23: DTO Catalog - request/response DTOs that are not 1:1 with an entity
A24: Booking Lifecycle - status transitions
A25: Practice Topics - interesting problems to practise
A26: Conventions - cross-cutting API, naming and DTO conventions
A27: Build Order - suggested implementation sequence

Sheet API Endpoints
A1: # | B1: Module | C1: Group | D1: Method | E1: Endpoint (under /api/v1) | F1: Purpose / Notes | G1: Status
A2: 1 | B2: Customer | C2: Auth & Users | D2: POST | E2: /auth/register | F2: Customer signup | G2: Not started
A3: 2 | B3: Customer | C3: Auth & Users | D3: POST | E3: /auth/login | F3: Returns access and refresh tokens | G3: Not started
A4: 3 | B4: Customer | C4: Auth & Users | D4: POST | E4: /auth/refresh-token | F4: Renew access token | G4: Not started
A5: 4 | B5: Customer | C5: Auth & Users | D5: POST | E5: /auth/logout | F5: Invalidate refresh token | G5: Not started
A6: 5 | B6: Customer | C6: Auth & Users | D6: POST | E6: /auth/forgot-password | F6: Send reset link | G6: Not started
A7: 6 | B7: Customer | C7: Auth & Users | D7: POST | E7: /auth/reset-password | F7: Set new password | G7: Not started
A8: 7 | B8: Customer | C8: Auth & Users | D8: GET | E8: /auth/verify-email?token= | F8: Email verification | G8: Not started
A9: 8 | B9: Customer | C9: Auth & Users | D9: GET | E9: /users/me | F9: Own profile | G9: Not started
A10: 9 | B10: Customer | C10: Auth & Users | D10: PUT | E10: /users/me | F10: Update profile | G10: Not started
A11: 10 | B11: Customer | C11: Auth & Users | D11: PATCH | E11: /users/me/password | F11: Change password | G11: Not started
A12: 11 | B12: Customer | C12: Auth & Users | D12: DELETE | E12: /users/me | F12: Delete or deactivate account | G12: Not started
A13: 12 | B13: Customer | C13: Destinations & Categories | D13: GET | E13: /destinations | F13: List destinations (public) | G13: Not started
... A130: 129 | B130: Admin | C130: Reports & Audit | D130: GET | E130: /admin/audit-logs | F130: Audit logs | G130: Not started

Sheet Domain Entities
A1: Entity (Java class) | B1: Table | C1: Module | D1: Description | E1: Field count
A2: User | B2: users | C2: Auth & Users | D2: Every account: customer, supplier or admin | E2: =COUNTIF('Entity Fields'!$A:$A,A2) -> 16
A3: VerificationToken | B3: verification_tokens | C3: Auth & Users | D3: One-time tokens for email verification and password reset | E3: =COUNTIF('Entity Fields'!$A:$A,A3) -> 7
A4: RefreshToken | B4: refresh_tokens | C4: Auth & Users | D4: JWT refresh tokens, revocable on logout | E4: =COUNTIF('Entity Fields'!$A:$A,A4) -> 7
A5: SupplierProfile | B5: supplier_profiles | C5: Auth & Users | D5: Company or guide that offers activities (1:1 with a SUPPLIER user) | E5: =COUNTIF('Entity Fields'!$A:$A,A5) -> 19
A6: Destination | B6: destinations | C6: Catalog | D6: City or region where activities take place | E6: =COUNTIF('Entity Fields'!$A:$A,A6) -> 14
A7: Category | B7: categories | C7: Catalog | D7: Activity category (supports parent/child tree) | E7: =COUNTIF('Entity Fields'!$A:$A,A7) -> 10
A8: Tag | B8: tags | C8: Catalog | D8: Free-form labels for activities | E8: =COUNTIF('Entity Fields'!$A:$A,A8) -> 4
A9: Activity | B9: activities | C9: Catalog | D9: A tour or experience: the main product | E9: =COUNTIF('Entity Fields'!$A:$A,A9) -> 31
A10: ActivityCategory | B10: activity_categories | C10: Catalog | D10: Join table Activity <-> Category (no entity class needed, use @ManyToMany) | E10: =COUNTIF('Entity Fields'!$A:$A,A10) -> 2
A11: ActivityTag | B11: activity_tags | C11: Catalog | D11: Join table Activity <-> Tag (no entity class needed, use @ManyToMany) | E11: =COUNTIF('Entity Fields'!$A:$A,A11) -> 2
A12: ActivityLanguage | B12: activity_languages | C12: Catalog | D12: Languages an activity is offered in (@ElementCollection) | E12: =COUNTIF('Entity Fields'!$A:$A,A12) -> 2
A13: ActivityMedia | B13: activity_media | C13: Catalog | D13: Images and videos of an activity | E13: =COUNTIF('Entity Fields'!$A:$A,A13) -> 8
... A34: AuditLog | B34: audit_logs | C34: Platform | D34: Who did what, for admin and sensitive actions | E34: =COUNTIF('Entity Fields'!$A:$A,A34) -> 10

Sheet Entity Fields
A1: Entity | B1: Table | C1: Java field | D1: DB column | E1: Java type | F1: PostgreSQL type | G1: Nullable | H1: Key | I1: References | J1: Default | K1: DB constraint | L1: Suggested validation | M1: Create DTO | N1: Update DTO | O1: Response DTO | P1: Notes
A2: User | B2: users | C2: id | D2: id | E2: Long | F2: BIGINT | G2: N | H2: PK | J2: GENERATED BY DEFAULT AS IDENTITY | O2: Y | P2: BIGSERIAL / @GeneratedValue(IDENTITY)
A3: User | B3: users | C3: email | D3: email | E3: String | F3: VARCHAR(255) | G3: N | H3: UK | L3: @NotBlank @Email @Size(max=255) | M3: Y | O3: Y | P3: Store lower-case; immutable after registration (not in update DTO)
A4: User | B4: users | C4: passwordHash | D4: password_hash | E4: String | F4: VARCHAR(255) | G4: N | L4: Validate the raw password on RegisterRequest: @Size(min=8,max=64) + @Pattern complexity | P4: BCrypt hash. Never exposed in any response DTO
A5: User | B5: users | C5: firstName | D5: first_name | E5: String | F5: VARCHAR(100) | G5: N | L5: @NotBlank @Size(max=100) | M5: Y | N5: Y | O5: Y
A6: User | B6: users | C6: lastName | D6: last_name | E6: String | F6: VARCHAR(100) | G6: N | L6: @NotBlank @Size(max=100) | M6: Y | N6: Y | O6: Y
A7: User | B7: users | C7: phoneNumber | D7: phone_number | E7: String | F7: VARCHAR(20) | G7: Y | L7: @Pattern(regexp=\"^\\+[1-9]\\d{6,14}$\") (E.164) | M7: Y | N7: Y | O7: Y
A8: User | B8: users | C8: dateOfBirth | D8: date_of_birth | E8: LocalDate | F8: DATE | G8: Y | L8: @Past | M8: Y | N8: Y | O8: Y
A9: User | B9: users | C9: role | D9: role | E9: Role | F9: VARCHAR(30) | G9: N | J9: 'CUSTOMER' | O9: Y | P9: Changed only via PATCH /admin/users/{id}/role
A10: User | B10: users | C10: status | D10: status | E10: UserStatus | F10: VARCHAR(30) | G10: N | J10: 'PENDING_VERIFICATION' | O10: Y | P10: Changed by email verification, admin block/unblock, account delete
A11: User | B11: users | C11: emailVerified | D11: email_verified | E11: Boolean | F11: BOOLEAN | G11: N | J11: false | O11: Y
A12: User | B12: users | C12: preferredLanguage | D12: preferred_language | E12: String | F12: VARCHAR(5) | G12: N | J12: 'en' | L12: @Pattern(regexp=\"^[a-z]{2}(-[A-Z]{2})?$\") | M12: Y | N12: Y | O12: Y
A13: User | B13: users | C13: preferredCurrency | D13: preferred_currency | E13: String | F13: VARCHAR(3) | G13: N | J13: 'EUR' | L13: @Pattern(regexp=\"^[A-Z]{3}$\") | M13: Y | N13: Y | O13: Y
A14: User | B14: users | C14: profileImageUrl | D14: profile_image_url | E14: String | F14: VARCHAR(500) | G14: Y | L14: @URL @Size(max=500) | N14: Y | O14: Y
A15: User | B15: users | C15: lastLoginAt | D15: last_login_at | E15: Instant | F15: TIMESTAMPTZ | G15: Y | O15: Y
A16: User | B16: users | C16: createdAt | D16: created_at | E16: Instant | F16: TIMESTAMPTZ | G16: N | J16: now() | L16: Set by auditing, never from client | O16: Y | P16: @CreatedDate
A17: User | B17: users | C17: updatedAt | D17: updated_at | E17: Instant | F17: TIMESTAMPTZ | G17: N | J17: now() | L17: Set by auditing, never from client | O17: Y | P17: @LastModifiedDate
A18: VerificationToken | B18: verification_tokens | C18: id | D18: id | E18: Long | F18: BIGINT | G18: N | H18: PK | J18: GENERATED BY DEFAULT AS IDENTITY | O18: Y | P18: BIGSERIAL / @GeneratedValue(IDENTITY)
A19: VerificationToken | B19: verification_tokens | C19: user | D19: user_id | E19: User | F19: BIGINT | G19: N | H19: FK | I19: users.id
A20: VerificationToken | B20: verification_tokens | C20: tokenHash | D20: token_hash | E20: String | F20: VARCHAR(100) | G20: N | H20: UK | P20: Store a hash, send the raw token by email
A21: VerificationToken | B21: verification_tokens | C21: type | D21: type | E21: TokenType | F21: VARCHAR(30) | G21: N
A22: VerificationToken | B22: verification_tokens | C22: expiresAt | D22: expires_at | E22: Instant | F22: TIMESTAMPTZ | G22: N
A23: VerificationToken | B23: verification_tokens | C23: usedAt | D23: used_at | E23: Instant | F23: TIMESTAMPTZ | G23: Y
A24: VerificationToken | B24: verification_tokens | C24: createdAt | D24: created_at | E24: Instant | F24: TIMESTAMPTZ | G24: N | J24: now() | L24: Set by auditing, never from client | O24: Y | P24: @CreatedDate
A25: RefreshToken | B25: refresh_tokens | C25: id | D25: id | E25: Long | F25: BIGINT | G25: N | H25: PK | J25: GENERATED BY DEFAULT AS IDENTITY | O25: Y | P25: BIGSERIAL / @GeneratedValue(IDENTITY)
A26: RefreshToken | B26: refresh_tokens | C26: user | D26: user_id | E26: User | F26: BIGINT | G26: N | H26: FK | I26: users.id
A27: RefreshToken | B27: refresh_tokens | C27: tokenHash | D27: token_hash | E27: String | F27: VARCHAR(255) | G27: N | H27: UK
A28: RefreshToken | B28: refresh_tokens | C28: expiresAt | D28: expires_at | E28: Instant | F28: TIMESTAMPTZ | G28: N
A29: RefreshToken | B29: refresh_tokens | C29: revoked | D29: revoked | E29: Boolean | F29: BOOLEAN | G29: N | J29: false
A30: RefreshToken | B30: refresh_tokens | C30: deviceInfo | D30: device_info | E30: String | F30: VARCHAR(300) | G30: Y | P30: User-Agent / device label
A31: RefreshToken | B31: refresh_tokens | C31: createdAt | D31: created_at | E31: Instant | F31: TIMESTAMPTZ | G31: N | J31: now() | L31: Set by auditing, never from client | O31: Y | P31: @CreatedDate
A32: SupplierProfile | B32: supplier_profiles | C32: id | D32: id | E32: Long | F32: BIGINT | G32: N | H32: PK | J32: GENERATED BY DEFAULT AS IDENTITY | O32: Y | P32: BIGSERIAL / @GeneratedValue(IDENTITY)
A33: SupplierProfile | B33: supplier_profiles | C33: user | D33: user_id | E33: User | F33: BIGINT | G33: N | H33: FK,UK | I33: users.id | O33: Y | P33: Taken from the authenticated user on /supplier/register
A34: SupplierProfile | B34: supplier_profiles | C34: companyName | D34: company_name | E34: String | F34: VARCHAR(200) | G34: N | L34: @NotBlank @Size(max=200) | M34: Y | N34: Y | O34: Y
A35: SupplierProfile | B35: supplier_profiles | C35: description | D35: description | E35: String | F35: TEXT | G35: Y | L35: @Size(max=4000) | M35: Y | N35: Y | O35: Y
A36: SupplierProfile | B36: supplier_profiles | C36: contactEmail | D36: contact_email | E36: String | F36: VARCHAR(255) | G36: N | L36: @NotBlank @Email | M36: Y | N36: Y | O36: Y
A37: SupplierProfile | B37: supplier_profiles | C37: contactPhone | D37: contact_phone | E37: String | F37: VARCHAR(20) | G37: Y | L37: @Pattern (E.164) | M37: Y | N37: Y | O37: Y
A38: SupplierProfile | B38: supplier_profiles | C38: website | D38: website | E38: String | F38: VARCHAR(255) | G38: Y | L38: @URL | M38: Y | N38: Y | O38: Y
A39: SupplierProfile | B39: supplier_profiles | C39: taxId | D39: tax_id | E39: String | F39: VARCHAR(50) | G39: Y | L39: @Size(max=50) | M39: Y | N39: Y | O39: Y | P39: VAT / tax number
A40: SupplierProfile | B40: supplier_profiles | C40: addressLine | D40: address_line | E40: String | F40: VARCHAR(255) | G40: Y | M40: Y | N40: Y | O40: Y
A41: SupplierProfile | B41: supplier_profiles | C41: city | D41: city | E41: String | F41: VARCHAR(100) | G41: Y | M41: Y | N41: Y | O41: Y
A42: SupplierProfile | B42: supplier_profiles | C42: postalCode | D42: postal_code | E42: String | F42: VARCHAR(20) | G42: Y | M42: Y | N42: Y | O42: Y
A43: SupplierProfile | B43: supplier_profiles | C43: countryCode | D43: country_code | E43: String | F43: VARCHAR(2) | G43: N | L43: @NotBlank @Pattern(regexp=\"^[A-Z]{2}$\") | M43: Y | N43: Y | O43: Y | P43: ISO 3166-1 alpha-2
A44: SupplierProfile | B44: supplier_profiles | C44: logoUrl | D44: logo_url | E44: String | F44: VARCHAR(500) | G44: Y | L44: @URL | N44: Y | O44: Y
A45: SupplierProfile | B45: supplier_profiles | C45: status | D45: status | E45: SupplierStatus | F45: VARCHAR(30) | G45: N | J45: 'PENDING' | O45: Y | P45: Changed via /admin/suppliers/{id}/approve|reject
A46: SupplierProfile | B46: supplier_profiles | C46: rejectionReason | D46: rejection_reason | E46: String | F46: VARCHAR(500) | G46: Y | O46: Y
A47: SupplierProfile | B47: supplier_profiles | C47: commissionRate | D47: commission_rate | E47: BigDecimal | F47: NUMERIC(5,2) | G47: N | J47: 15.00 | K47: CHECK (commission_rate BETWEEN 0 AND 100) | O47: Y | P47: Percentage the platform keeps; set by admin
A48: SupplierProfile | B48: supplier_profiles | C48: approvedAt | D48: approved_at | E48: Instant | F48: TIMESTAMPTZ | G48: Y | O48: Y
A49: SupplierProfile | B49: supplier_profiles | C49: createdAt | D49: created_at | E49: Instant | F49: TIMESTAMPTZ | G49: N | J49: now() | L49: Set by auditing, never from client | O49: Y | P49: @CreatedDate
A50: SupplierProfile | B50: supplier_profiles | C50: updatedAt | D50: updated_at | E50: Instant | F50: TIMESTAMPTZ | G50: N | J50: now() | L50: Set by auditing, never from client | O50: Y | P50: @LastModifiedDate
A51: Destination | B51: destinations | C51: id | D51: id | E51: Long | F51: BIGINT | G51: N | H51: PK | J51: GENERATED BY DEFAULT AS IDENTITY | O51: Y | P51: BIGSERIAL / @GeneratedValue(IDENTITY)
A52: Destination | B52: destinations | C52: name | D52: name | E52: String | F52: VARCHAR(150) | G52: N | L52: @NotBlank @Size(max=150) | M52: Y | N52: Y | O52: Y
A53: Destination | B53: destinations | C53: slug | D53: slug | E53: String | F53: VARCHAR(180) | G53: N | H53: UK | O53: Y | P53: Generated from name
A54: Destination | B54: destinations | C54: country | D54: country | E54: String | F54: VARCHAR(100) | G54: N | L54: @NotBlank | M54: Y | N54: Y | O54: Y
A55: Destination | B55: destinations | C55: countryCode | D55: country_code | E55: String | F55: VARCHAR(2) | G55: N | L55: @NotBlank @Pattern(regexp=\"^[A-Z]{2}$\") | M55: Y | N55: Y | O55: Y
A56: Destination | B56: destinations | C56: timezone | D56: timezone | E56: String | F56: VARCHAR(50) | G56: N | L56: @NotBlank + custom check ZoneId.of() | M56: Y | N56: Y | O56: Y | P56: e.g. Europe/Paris, used for slot times
A57: Destination | B57: destinations | C57: description | D57: description | E57: String | F57: TEXT | G57: Y | M57: Y | N57: Y | O57: Y
A58: Destination | B58: destinations | C58: latitude | D58: latitude | E58: BigDecimal | F58: NUMERIC(9,6) | G58: Y | L58: @DecimalMin(-90) @DecimalMax(90) | M58: Y | N58: Y | O58: Y
A59: Destination | B59: destinations | C59: longitude | D59: longitude | E59: BigDecimal | F59: NUMERIC(9,6) | G59: Y | L59: @DecimalMin(-180) @DecimalMax(180) | M59: Y | N59: Y | O59: Y
A60: Destination | B60: destinations | C60: imageUrl | D60: image_url | E60: String | F60: VARCHAR(500) | G60: Y | L60: @URL | M60: Y | N60: Y | O60: Y
A61: Destination | B61: destinations | C61: popular | D61: popular | E61: Boolean | F61: BOOLEAN | G61: N | J61: false | M61: Y | N61: Y | O61: Y
A62: Destination | B62: destinations | C62: active | D62: active | E62: Boolean | F62: BOOLEAN | G62: N | J62: true | M62: Y | N62: Y | O62: Y
A63: Destination | B63: destinations | C63: createdAt | D63: created_at | E63: Instant | F63: TIMESTAMPTZ | G63: N | J63: now() | L63: Set by auditing, never from client | O63: Y | P63: @CreatedDate
A64: Destination | B64: destinations | C64: updatedAt | D64: updated_at | E64: Instant | F64: TIMESTAMPTZ | G64: N | J64: now() | L64: Set by auditing, never from client | O64: Y | P64: @LastModifiedDate
A65: Category | B65: categories | C65: id | D65: id | E65: Long | F65: BIGINT | G65: N | H65: PK | J65: GENERATED BY DEFAULT AS IDENTITY | O65: Y | P65: BIGSERIAL / @GeneratedValue(IDENTITY)
A66: Category | B66: categories | C66: name | D66: name | E66: String | F66: VARCHAR(100) | G66: N | H66: UK | L66: @NotBlank @Size(max=100) | M66: Y | N66: Y | O66: Y
A67: Category | B67: categories | C67: slug | D67: slug | E67: String | F67: VARCHAR(120) | G67: N | H67: UK | O67: Y
A68: Category | B68: categories | C68: description | D68: description | E68: String | F68: VARCHAR(500) | G68: Y | M68: Y | N68: Y | O68: Y
A69: Category | B69: categories | C69: iconUrl | D69: icon_url | E69: String | F69: VARCHAR(500) | G69: Y | L69: @URL | M69: Y | N69: Y | O69: Y
A70: Category | B70: categories | C70: parent | D70: parent_id | E70: Category | F70: BIGINT | G70: Y | H70: FK | I70: categories.id | M70: Y | N70: Y | O70: Y | P70: Self reference; DTO exposes parentId
A71: Category | B71: categories | C71: displayOrder | D71: display_order | E71: Integer | F71: INTEGER | G71: N | J71: 0 | M71: Y | N71: Y | O71: Y
A72: Category | B72: categories | C72: active | D72: active | E72: Boolean | F72: BOOLEAN | G72: N | J72: true | M72: Y | N72: Y | O72: Y
A73: Category | B73: categories | C73: createdAt | D73: created_at | E73: Instant | F73: TIMESTAMPTZ | G73: N | J73: now() | L73: Set by auditing, never from client | O73: Y | P73: @CreatedDate
A74: Category | B74: categories | C74: updatedAt | D74: updated_at | E74: Instant | F74: TIMESTAMPTZ | G74: N | J74: now() | L74: Set by auditing, never from client | O74: Y | P74: @LastModifiedDate
A75: Tag | B75: tags | C75: id | D75: id | E75: Long | F75: BIGINT | G75: N | H75: PK | J75: GENERATED BY DEFAULT AS IDENTITY | O75: Y | P75: BIGSERIAL / @GeneratedValue(IDENTITY)
A76: Tag | B76: tags | C76: name | D76: name | E76: String | F76: VARCHAR(50) | G76: N | H76: UK | L76: @NotBlank @Size(max=50) | M76: Y | N76: Y | O76: Y
A77: Tag | B77: tags | C77: slug | D77: slug | E77: String | F77: VARCHAR(60) | G77: N | H77: UK | O77: Y
A78: Tag | B78: tags | C78: createdAt | D78: created_at | E78: Instant | F78: TIMESTAMPTZ | G78: N | J78: now() | L78: Set by auditing, never from client | O78: Y | P78: @CreatedDate
A79: Activity | B79: activities | C79: id | D79: id | E79: Long | F79: BIGINT | G79: N | H79: PK | J79: GENERATED BY DEFAULT AS IDENTITY | O79: Y | P79: BIGSERIAL / @GeneratedValue(IDENTITY)
A80: Activity | B80: activities | C80: supplier | D80: supplier_id | E80: SupplierProfile | F80: BIGINT | G80: N | H80: FK | I80: supplier_profiles.id | O80: Y | P80: Taken from authenticated supplier
A81: Activity | B81: activities | C81: destination | D81: destination_id | E81: Destination | F81: BIGINT | G81: N | H81: FK | I81: destinations.id | M81: Y | N81: Y | O81: Y | P81: DTO exposes destinationId
A82: Activity | B82: activities | C82: title | D82: title | E82: String | F82: VARCHAR(200) | G82: N | L82: @NotBlank @Size(min=5,max=200) | M82: Y | N82: Y | O82: Y
A83: Activity | B83: activities | C83: slug | D83: slug | E83: String | F83: VARCHAR(220) | G83: N | H83: UK | O83: Y | P83: Generated from title, made unique with suffix
A84: Activity | B84: activities | C84: shortDescription | D84: short_description | E84: String | F84: VARCHAR(500) | G84: N | L84: @NotBlank @Size(max=500) | M84: Y | N84: Y | O84: Y
A85: Activity | B85: activities | C85: description | D85: description | E85: String | F85: TEXT | G85: N | L85: @NotBlank @Size(max=10000) | M85: Y | N85: Y | O85: Y
A86: Activity | B86: activities | C86: highlights | D86: highlights | E86: String | F86: TEXT | G86: Y | M86: Y | N86: Y | O86: Y | P86: Newline separated or JSON array
A87: Activity | B87: activities | C87: included | D87: included | E87: String | F87: TEXT | G87: Y | M87: Y | N87: Y | O87: Y | P87: What is included
A88: Activity | B88: activities | C88: notIncluded | D88: not_included | E88: String | F88: TEXT | G88: Y | M88: Y | N88: Y | O88: Y
A89: Activity | B89: activities | C89: importantInfo | D89: important_info | E89: String | F89: TEXT | G89: Y | M89: Y | N89: Y | O89: Y
A90: Activity | B90: activities | C90: meetingPoint | D90: meeting_point | E90: String | F90: VARCHAR(300) | G90: Y | M90: Y | N90: Y | O90: Y
A91: Activity | B91: activities | C91: meetingLatitude | D91: meeting_latitude | E91: BigDecimal | F91: NUMERIC(9,6) | G91: Y | L91: @DecimalMin(-90) @DecimalMax(90) | M91: Y | N91: Y | O91: Y
A92: Activity | B92: activities | C92: meetingLongitude | D92: meeting_longitude | E92: BigDecimal | F92: NUMERIC(9,6) | G92: Y | L92: @DecimalMin(-180) @DecimalMax(180) | M92: Y | N92: Y | O92: Y
A93: Activity | B93: activities | C93: durationMinutes | D93: duration_minutes | E93: Integer | F93: INTEGER | G93: N | K93: CHECK (duration_minutes > 0) | L93: @NotNull @Positive | M93: Y | N93: Y | O93: Y
A94: Activity | B94: activities | C94: minParticipants | D94: min_participants | E94: Integer | F94: INTEGER | G94: N | J94: 1 | K94: CHECK (min_participants >= 1) | L94: @Min(1) | M94: Y | N94: Y | O94: Y
A95: Activity | B95: activities | C95: maxGroupSize | D95: max_group_size | E95: Integer | F95: INTEGER | G95: Y | L95: @Positive | M95: Y | N95: Y | O95: Y
A96: Activity | B96: activities | C96: minAge | D96: min_age | E96: Integer | F96: INTEGER | G96: Y | L96: @PositiveOrZero | M96: Y | N96: Y | O96: Y
A97: Activity | B97: activities | C97: basePrice | D97: base_price | E97: BigDecimal | F97: NUMERIC(10,2) | G97: N | K97: CHECK (base_price >= 0) | L97: @NotNull @PositiveOrZero @Digits(integer=8,fraction=2) | M97: Y | N97: Y | O97: Y | P97: 'From' price shown in listings
A98: Activity | B98: activities | C98: currency | D98: currency | E98: String | F98: VARCHAR(3) | G98: N | J98: 'EUR' | L98: @Pattern(regexp=\"^[A-Z]{3}$\") | M98: Y | N98: Y | O98: Y
A99: Activity | B99: activities | C99: instantConfirmation | D99: instant_confirmation | E99: Boolean | F99: BOOLEAN | G99: N | J99: true | M99: Y | N99: Y | O99: Y | P99: false = supplier must confirm each booking
A100: Activity | B100: activities | C100: freeCancellationHours | D100: free_cancellation_hours | E100: Integer | F100: INTEGER | G100: Y | L100: @PositiveOrZero | M100: Y | N100: Y | O100: Y | P100: Free cancel until N hours before start; null = not refundable
...

Sheet Relationships
A1: From entity | B1: Cardinality | C1: To entity | D1: FK column / join table | E1: Owning side | F1: JPA notes
A2: User | B2: 1 : 1 | C2: SupplierProfile | D2: supplier_profiles.user_id | E2: SupplierProfile | F2: Only for role SUPPLIER
A3: User | B3: 1 : N | C3: VerificationToken | D3: verification_tokens.user_id | E3: VerificationToken | F3: Delete tokens with the user
A4: User | B4: 1 : N | C4: RefreshToken | D4: refresh_tokens.user_id | E4: RefreshToken | F4: Delete tokens with the user
A5: User | B5: 1 : 1 | C5: Cart | D5: carts.user_id | E5: Cart | F5: Create lazily on first add-to-cart
A6: User | B6: 1 : N | C6: Booking | D6: bookings.user_id | E6: Booking | F6: Never cascade delete
A7: User | B7: 1 : N | C7: Review | D7: reviews.user_id | E7: Review
A8: User | B8: 1 : N | C8: WishlistItem | D8: wishlist_items.user_id | E8: WishlistItem
A9: User | B9: 1 : N | C9: Notification | D9: notifications.user_id | E9: Notification
A10: User | B10: 1 : 1 | C10: NotificationPreference | D10: notification_preferences.user_id | E10: NotificationPreference | F10: Create on registration
A11: User | B11: 1 : N | C11: AuditLog | D11: audit_logs.actor_id | E11: AuditLog | F11: Optional actor
A12: SupplierProfile | B12: 1 : N | C12: Activity | D12: activities.supplier_id | E12: Activity
A13: SupplierProfile | B13: 1 : N | C13: Booking | D13: bookings.supplier_id | E13: Booking | F13: Denormalised for supplier queries
A14: SupplierProfile | B14: 1 : N | C14: SupplierPayout | D14: supplier_payouts.supplier_id | E14: SupplierPayout
A15: Destination | B15: 1 : N | C15: Activity | D15: activities.destination_id | E15: Activity
A16: Category | B16: 1 : N | C16: Category | D16: categories.parent_id | E16: Category (child) | F16: Self reference for category tree
A17: Activity | B17: N : N | C17: Category | D17: activity_categories | E17: Activity | F17: @ManyToMany + @JoinTable
A18: Activity | B18: N : N | C18: Tag | D18: activity_tags | E18: Activity | F18: @ManyToMany + @JoinTable
A19: Activity | B19: 1 : N | C19: ActivityLanguage | D19: activity_languages.activity_id | E19: Activity | F19: @ElementCollection of language codes
A20: Activity | B20: 1 : N | C20: ActivityMedia | D20: activity_media.activity_id | E20: ActivityMedia | F20: cascade ALL + orphanRemoval
A21: Activity | B21: 1 : N | C21: PricingTier | D21: pricing_tiers.activity_id | E21: PricingTier | F21: cascade ALL
A22: Activity | B22: 1 : N | C22: TimeSlot | D22: time_slots.activity_id | E22: TimeSlot | F22: Do not cascade delete; slots may have bookings
A23: Activity | B23: 1 : N | C23: BlockedDate | D23: blocked_dates.activity_id | E23: BlockedDate
A24: Activity | B24: 1 : N | C24: Review | D24: reviews.activity_id | E24: Review
A25: Activity | B25: 1 : N | C25: WishlistItem | D25: wishlist_items.activity_id | E25: WishlistItem
A26: Cart | B26: 1 : N | C26: CartItem | D26: cart_items.cart_id | E26: CartItem | F26: cascade ALL + orphanRemoval
A27: CartItem | B27: N : 1 | C27: TimeSlot | D27: cart_items.time_slot_id | E27: CartItem | F27: LAZY
A28: CartItem | B28: N : 1 | C28: PricingTier | D28: cart_items.pricing_tier_id | E28: CartItem | F28: LAZY
A29: Cart | B29: N : 1 | C29: Coupon | D29: carts.coupon_id | E29: Cart | F29: Optional
A30: Booking | B30: 1 : N | C30: BookingItem | D30: booking_items.booking_id | E30: BookingItem | F30: cascade ALL
A31: Booking | B31: 1 : N | C31: Participant | D31: booking_participants.booking_id | E31: Participant | F31: cascade ALL + orphanRemoval
A32: Booking | B32: 1 : N | C32: Payment | D32: payments.booking_id | E32: Payment | F32: Several attempts possible
A33: Booking | B33: 1 : 0..1 | C33: Review | D33: reviews.booking_id | E33: Review | F33: One review per booking
A34: Booking | B34: N : 1 | C34: Coupon | D34: bookings.coupon_id | E34: Booking | F34: Optional
A35: BookingItem | B35: N : 1 | C35: TimeSlot | D35: booking_items.time_slot_id | E35: BookingItem | F35: The row you lock when booking
A36: BookingItem | B36: N : 1 | C36: PricingTier | D36: booking_items.pricing_tier_id | E36: BookingItem
A37: BookingItem | B37: N : 1 | C37: Activity | D37: booking_items.activity_id | E37: BookingItem | F37: Denormalised
A38: Participant | B38: N : 1 | C38: PricingTier | D38: booking_participants.pricing_tier_id | E38: Participant | F38: Optional
A39: Payment | B39: 1 : N | C39: Refund | D39: refunds.payment_id | E39: Refund
A40: Payment | B40: 1 : N | C40: PaymentWebhookEvent | D40: payment_webhook_events.payment_id | E40: PaymentWebhookEvent | F40: Optional
A41: Booking | B41: 1 : N | C41: Refund | D41: refunds.booking_id | E41: Refund
A42: Review | B42: 1 : N | C42: ReviewHelpfulVote | D42: review_helpful_votes.review_id | E42: ReviewHelpfulVote
A43: Review | B43: 1 : N | C43: ReviewReport | D43: review_reports.review_id | E43: ReviewReport
A44: Coupon | B44: 1 : N | C44: CouponRedemption | D44: coupon_redemptions.coupon_id | E44: CouponRedemption
A45: Booking | B45: 1 : 0..1 | C45: CouponRedemption | D45: coupon_redemptions.booking_id | E45: CouponRedemption

Sheet Enums
A1: Enum | B1: Value | C1: Used by (Entity.field)
A2: Role | B2: CUSTOMER | C2: User.role
A3: Role | B3: SUPPLIER | C3: User.role
A4: Role | B4: ADMIN | C4: User.role
A5: UserStatus | B5: PENDING_VERIFICATION | C5: User.status
A6: UserStatus | B6: ACTIVE | C6: User.status
A7: UserStatus | B7: BLOCKED | C7: User.status
A8: UserStatus | B8: DELETED | C8: User.status
A9: TokenType | B9: EMAIL_VERIFICATION | C9: VerificationToken.type
A10: TokenType | B10: PASSWORD_RESET | C10: VerificationToken.type
A11: SupplierStatus | B11: PENDING | C11: SupplierProfile.status
A12: SupplierStatus | B12: APPROVED | C12: SupplierProfile.status
... A80: NotificationType | B80: SYSTEM | C80: Notification.type

Sheet Constraints & Indexes
A1: Table | B1: Name | C1: Type | D1: Columns / expression | E1: Purpose
A2: users | B2: uk_users_email | C2: UNIQUE | D2: email | E2: No duplicate accounts; lookup on login
A3: users | B3: idx_users_status | C3: INDEX | D3: status | E3: Admin filtering
A4: verification_tokens | B4: uk_verification_token_hash | C4: UNIQUE | D4: token_hash | E4: Token lookup
A5: verification_tokens | B5: idx_verification_user_type | C5: INDEX | D5: user_id, type | E5: Invalidate older tokens
A6: refresh_tokens | B6: uk_refresh_token_hash | C6: UNIQUE | D6: token_hash | E6: Token lookup
A7: refresh_tokens | B7: idx_refresh_user | C7: INDEX | D7: user_id | E7: Revoke all on password change
A8: supplier_profiles | B8: uk_supplier_user | C8: UNIQUE | D8: user_id | E8: One profile per user
A9: supplier_profiles | B9: idx_supplier_status | C9: INDEX | D9: status | E9: Admin pending list
A10: supplier_profiles | B10: chk_supplier_commission | C10: CHECK | D10: commission_rate BETWEEN 0 AND 100 | E10: Valid percentage
A11: destinations | B11: uk_destination_slug | C11: UNIQUE | D11: slug | E11: SEO lookup
A12: destinations | B12: idx_destination_popular | C12: INDEX | D12: popular, active | E12: Popular destinations endpoint
A13: categories | B13: uk_category_name | C13: UNIQUE | D13: name
A14: categories | B14: uk_category_slug | C14: UNIQUE | D14: slug
A15: tags | B15: uk_tag_name | C15: UNIQUE | D15: name
A16: activities | B16: uk_activity_slug | C16: UNIQUE | D16: slug | E16: GET /activities/slug/{slug}
A17: activities | B17: idx_activity_dest_status | C17: INDEX | D17: destination_id, status | E17: Listing by destination
A18: activities | B18: idx_activity_supplier | C18: INDEX | D18: supplier_id, status | E18: Supplier 'my activities'
A19: activities | B19: idx_activity_featured | C19: INDEX (partial) | D19: featured WHERE status = 'ACTIVE' | E19: Homepage
A20: activities | B20: idx_activity_search | C20: INDEX (GIN) | D20: to_tsvector('simple', title || ' ' || short_description) | E20: Keyword search (or pg_trgm)
A21: activities | B21: chk_activity_price | C21: CHECK | D21: base_price >= 0
A22: activities | B22: chk_activity_duration | C22: CHECK | D22: duration_minutes > 0
A23: activities | B23: chk_activity_rating | C23: CHECK | D23: average_rating BETWEEN 0 AND 5
A24: activity_categories | B24: pk_activity_categories | C24: PRIMARY KEY | D24: activity_id, category_id
A25: activity_categories | B25: idx_activity_cat_category | C25: INDEX | D25: category_id | E25: Activities by category
A26: activity_tags | B26: pk_activity_tags | C26: PRIMARY KEY | D26: activity_id, tag_id
A27: activity_languages | B27: pk_activity_languages | C27: PRIMARY KEY | D27: activity_id, language_code
A28: activity_media | B28: idx_media_activity_order | C28: INDEX | D28: activity_id, display_order | E28: Gallery
A29: pricing_tiers | B29: uk_tier_activity_name | C29: UNIQUE | D29: activity_id, name
A30: pricing_tiers | B30: chk_tier_price | C30: CHECK | D30: price >= 0
A31: time_slots | B31: uk_slot_activity_date_time | C31: UNIQUE | D31: activity_id, slot_date, start_time | E31: No duplicate slots
A32: time_slots | B32: idx_slot_activity_date | C32: INDEX | D32: activity_id, slot_date | E32: Availability calendar
A33: time_slots | B33: chk_slot_capacity | C33: CHECK | D33: capacity > 0
A34: time_slots | B34: chk_slot_booked | C34: CHECK | D34: booked_count >= 0 AND booked_count <= capacity | E34: Last line of defence against overbooking
A35: time_slots | B35: chk_slot_times | C35: CHECK | D35: end_time > start_time
A36: blocked_dates | B36: uk_blocked_activity_date | C36: UNIQUE | D36: activity_id, blocked_date
A37: carts | B37: uk_cart_user | C37: UNIQUE | D37: user_id | E37: One cart per user
A38: cart_items | B38: uk_cart_item | C38: UNIQUE | D38: cart_id, time_slot_id, pricing_tier_id | E38: Merge duplicates into quantity
A39: cart_items | B39: chk_cart_item_qty | C39: CHECK | D39: quantity > 0
A40: bookings | B40: uk_booking_reference | C40: UNIQUE | D40: booking_reference | E40: Lookup by reference
A41: bookings | B41: uk_booking_idempotency | C41: UNIQUE | D41: idempotency_key | E41: Idempotent create
A42: bookings | B42: idx_booking_user_status | C42: INDEX | D42: user_id, status, created_at DESC | E42: My bookings
A43: bookings | B43: idx_booking_supplier_status | C43: INDEX | D43: supplier_id, status | E43: Supplier bookings
A44: bookings | B44: idx_booking_hold_expiry | C44: INDEX (partial) | D44: hold_expires_at WHERE status = 'PENDING' | E44: Expiry scheduler
A45: bookings | B45: chk_booking_total | C45: CHECK | D45: total_amount >= 0
A46: booking_items | B46: idx_booking_item_booking | C46: INDEX | D46: booking_id
A47: booking_items | B47: idx_booking_item_slot | C47: INDEX | D47: time_slot_id | E47: Seats per slot
A48: booking_items | B48: chk_booking_item_qty | C48: CHECK | D48: quantity > 0
A49: booking_participants | B49: idx_participant_booking | C49: INDEX | D49: booking_id
A50: coupons | B50: uk_coupon_code | C50: UNIQUE | D50: code
A51: coupons | B51: chk_coupon_value | C51: CHECK | D51: discount_value > 0
A52: coupons | B52: chk_coupon_dates | C52: CHECK | D52: valid_until > valid_from
A53: coupon_redemptions | B53: uk_redemption_coupon_booking | C53: UNIQUE | D53: coupon_id, booking_id
A54: coupon_redemptions | B54: idx_redemption_coupon_user | C54: INDEX | D54: coupon_id, user_id | E54: Per-user limit check
A55: payments | B55: uk_payment_reference | C55: UNIQUE | D55: payment_reference
A56: payments | B56: uk_payment_provider_txn | C56: UNIQUE | D56: provider_transaction_id
A57: payments | B57: uk_payment_idempotency | C57: UNIQUE | D57: idempotency_key
A58: payments | B58: idx_payment_booking | C58: INDEX | D58: booking_id
A59: payments | B59: chk_payment_amount | C59: CHECK | D59: amount > 0
A60: payment_webhook_events | B60: uk_webhook_event | C60: UNIQUE | D60: provider_event_id | E60: Webhook idempotency
A61: refunds | B61: idx_refund_payment | C61: INDEX | D61: payment_id
A62: refunds | B62: chk_refund_amount | C62: CHECK | D62: amount > 0
A63: supplier_payouts | B63: idx_payout_supplier_period | C63: INDEX | D63: supplier_id, period_start
A64: supplier_payouts | B64: chk_payout_net | C64: CHECK | D64: net_amount = gross_amount - commission_amount
A65: reviews | B65: uk_review_booking | C65: UNIQUE | D65: booking_id | E65: One review per booking
A66: reviews | B66: idx_review_activity_status | C66: INDEX | D66: activity_id, status, created_at DESC | E66: Review listing
A67: reviews | B67: chk_review_rating | C67: CHECK | D67: rating BETWEEN 1 AND 5
A68: review_helpful_votes | B68: uk_vote_review_user | C68: UNIQUE | D68: review_id, user_id | E68: One vote per user
A69: review_reports | B69: uk_report_review_reporter | C69: UNIQUE | D69: review_id, reporter_id | E69: One report per user
A70: review_reports | B70: idx_report_status | C70: INDEX | D70: status | E70: Admin queue
A71: wishlist_items | B71: uk_wishlist_user_activity | C71: UNIQUE | D71: user_id, activity_id
A72: notifications | B72: idx_notification_user_unread | C72: INDEX | D72: user_id, is_read, created_at DESC | E72: Inbox
A73: notification_preferences | B73: uk_notif_pref_user | C73: UNIQUE | D73: user_id
A74: audit_logs | B74: idx_audit_entity | C74: INDEX | D74: entity_type, entity_id
A75: audit_logs | B75: idx_audit_actor_time | C75: INDEX | D75: actor_id, created_at DESC

Sheet Booking Lifecycle
A1: From | B1: To | C1: Trigger
A2: PENDING | B2: CONFIRMED | C2: Payment success, activity has instantConfirmation = true
A3: PENDING | B3: AWAITING_CONFIRMATION | C3: Payment success, activity has instantConfirmation = false
A4: AWAITING_CONFIRMATION | B4: CONFIRMED | C4: Supplier confirms (PATCH /supplier/bookings/{id}/confirm)
A5: AWAITING_CONFIRMATION | B5: REJECTED | C5: Supplier rejects (refund the payment)
A6: CONFIRMED | B6: COMPLETED | C6: Activity attended / supplier marks complete
A7: PENDING | B7: EXPIRED | C7: Hold timeout (e.g. 15 minutes); release slot capacity
A8: CONFIRMED | B8: CANCELLED | C8: Customer or admin cancels
A9: CANCELLED | B9: REFUNDED | C9: Refund processed
A11: Note: model this as an enum with allowed transitions and reject illegal ones with 409 Conflict.

Sheet DTO Catalog
A1: DTO class | B1: Kind | C1: Used by endpoint | D1: Fields (name:type, ? = optional)
A2: RegisterRequest | B2: Request | C2: POST /auth/register | D2: email:String, password:String, firstName:String, lastName:String, phoneNumber:String?, preferredLanguage:String?
A3: LoginRequest | B3: Request | C3: POST /auth/login | D3: email:String, password:String
A4: AuthResponse | B4: Response | C4: POST /auth/login, /auth/refresh-token | D4: accessToken:String, refreshToken:String, tokenType:String, expiresInSeconds:Long, user:UserResponse
A5: RefreshTokenRequest | B5: Request | C5: POST /auth/refresh-token, /auth/logout | D5: refreshToken:String
A6: ForgotPasswordRequest | B6: Request | C6: POST /auth/forgot-password | D6: email:String
A7: ResetPasswordRequest | B7: Request | C7: POST /auth/reset-password | D7: token:String, newPassword:String
A8: ChangePasswordRequest | B8: Request | C8: PATCH /users/me/password | D8: currentPassword:String, newPassword:String
A9: PageResponse<T> | B9: Response | C9: All list endpoints | D9: content:List<T>, page:int, size:int, totalElements:long, totalPages:int, last:boolean
A10: ErrorResponse | B10: Response | C10: All error cases | D10: timestamp:Instant, status:int, errorCode:String, message:String, fieldErrors:List<FieldErrorDto>, path:String
A11: FieldErrorDto | B11: Response | C11: Inside ErrorResponse | D11: field:String, message:String, rejectedValue:Object
A12: ActivitySearchCriteria | B12: Request (query params) | C12: GET /activities, /activities/search | D12: q:String?, destinationId:Long?, categoryId:Long?, minPrice:BigDecimal?, maxPrice:BigDecimal?, minRating:BigDecimal?, minDurationMinutes:Integer?, maxDurationMinutes:Integer?, language:String?, date:LocalDate?, freeCancellation:Boolean?, instantConfirmation:Boolean?, sortBy:String?, sortDir:String?, page:int, size:int
... A44: UserGrowthResponse | B44: Response | C44: GET /admin/reports/user-growth | D44: period:String, newUsers:long, totalUsers:long

Sheet Practice Topics
A1: Topic | B1: What to practise | C1: Done?
A2: Overbooking prevention | B2: Pessimistic locking (@Lock) or optimistic locking (@Version) on TimeSlot capacity | C2: No
A3: Slot hold with expiry | B3: @Scheduled job that expires PENDING bookings after 15 minutes and releases capacity | C3: No
A4: Idempotency | B4: Idempotency-Key header for payment and booking creation | C4: No
A5: Dynamic pricing | B5: Weekend or peak pricing, group discounts, coupon rules | C5: No
A6: Refund policy engine | B6: e.g. 100% refund over 24h before start, 0% after | C6: No
A7: Dynamic filtering | B7: JPA Specifications or Criteria API for /activities | C7: No
A8: N+1 problems | B8: Entity graphs, DTO projections on listing endpoints | C8: No
A9: Soft deletes & auditing | B9: createdAt, updatedAt, createdBy | C9: No
A10: Multi-currency & i18n | B10: Activity descriptions and prices in multiple languages/currencies | C10: No
A11: Role-based security | B11: Spring Security + JWT, plus ownership checks (supplier touches only own activities) | C11: No
A12: Async work | B12: Booking confirmation emails and notifications via events or Kafka | C12: No
A13: Caching | B13: Destinations, categories, featured activities | C13: No

Sheet Conventions
A1: Area | B1: Convention
A2: Error format | B2: timestamp, status, errorCode, message, fieldErrors[], path
A3: Status codes | B3: 201 create, 204 delete, 400 validation, 401/403 auth, 404 missing, 409 conflict (slot full, invalid transition), 422 business rule violation
A4: Pagination envelope | B4: content, page, size, totalElements, totalPages
A5: Booking reference | B5: Human-friendly code (e.g. GYG-8F3K2Q) rather than DB id
A6: DTOs | B6: Separate request and response DTOs from entities
A7: Docs & migrations | B7: OpenAPI/Swagger and Flyway migrations from day one
A8: Versioning | B8: Prefix every endpoint with /api/v1
A9: Primary keys | B9: BIGINT identity (Long) for every table except pure join tables, which use composite PKs
A10: Naming | B10: Tables: plural snake_case. Columns: snake_case. FK columns: <entity>_id. Constraints: pk_/uk_/idx_/chk_ prefix
A11: Timestamps | B11: Use Instant mapped to TIMESTAMPTZ; store UTC, convert to destination timezone only for display
A12: Money | B12: BigDecimal mapped to NUMERIC; never double/float. Currency as ISO 4217 code
... A17: Fetching | B17: Use LAZY for all @ManyToOne/@OneToMany; load with entity graphs or DTO projections to avoid N+1

Sheet Build Order
A1: Step | B1: Module | C1: Done?
A2: 1 | B2: Auth and users | C2: No
A3: 2 | B3: Destinations, categories, activities (CRUD plus search) | C3: No
A4: 3 | B4: Time slots and availability | C4: No
A5: 4 | B5: Cart and booking creation with slot locking | C5: No
A6: 5 | B6: Mock payments and booking lifecycle | C6: No
A7: 6 | B7: Cancellation and refunds | C7: No
A8: 7 | B8: Reviews and wishlist | C8: No
A9: 8 | B9: Supplier module and admin approvals | C9: No
A10: 9 | B10: Notifications, reports, caching, scheduled jobs | C10: No
